zope.app.tree-4.1.0-py3.7-nspkg.pth
zope/app/tree/README.rst
zope/app/tree/__init__.py
zope/app/tree/adapters.py
zope/app/tree/configure.zcml
zope/app/tree/filters.py
zope/app/tree/interfaces.py
zope/app/tree/node.py
zope/app/tree/utils.py
zope/app/tree/browser/__init__.py
zope/app/tree/browser/configure.zcml
zope/app/tree/browser/cookie.py
zope/app/tree/browser/example1.pt
zope/app/tree/browser/ftesting.zcml
zope/app/tree/browser/navigation_macros.pt
zope/app/tree/browser/tests.py
zope/app/tree/browser/images/lline.png
zope/app/tree/browser/images/minus.png
zope/app/tree/browser/images/minus_vline.png
zope/app/tree/browser/images/plus.png
zope/app/tree/browser/images/plus_vline.png
zope/app/tree/browser/images/shim.gif
zope/app/tree/browser/images/tline.png
zope/app/tree/browser/images/vline.png
zope/app/tree/tests/__init__.py
zope/app/tree/tests/basetest.py
zope/app/tree/tests/test_adapters.py
zope/app/tree/tests/test_encoder.py
zope/app/tree/tests/test_filters.py
zope/app/tree/tests/test_node.py
zope/app/tree/tests/test_utils.py
zope.app.tree-4.1.0.dist-info/METADATA
zope.app.tree-4.1.0.dist-info/WHEEL
zope.app.tree-4.1.0.dist-info/namespace_packages.txt
zope.app.tree-4.1.0.dist-info/top_level.txt
zope.app.tree-4.1.0.dist-info/RECORD
