Metadata-Version: 2.1
Name: zope.app.tree
Version: 4.1.0
Summary: Static Tree Implementation
Home-page: http://github.com/zopefoundation/zope.app.tree
Author: Zope Foundation and Contributors
Author-email: zope-dev@zope.org
License: ZPL 2.1
Keywords: zope3 tree static zpt
Platform: UNKNOWN
Classifier: Development Status :: 5 - Production/Stable
Classifier: Environment :: Web Environment
Classifier: Intended Audience :: Developers
Classifier: License :: OSI Approved :: Zope Public License
Classifier: Programming Language :: Python
Classifier: Programming Language :: Python :: 2
Classifier: Programming Language :: Python :: 2.7
Classifier: Programming Language :: Python :: 3
Classifier: Programming Language :: Python :: 3.5
Classifier: Programming Language :: Python :: 3.6
Classifier: Programming Language :: Python :: 3.7
Classifier: Programming Language :: Python :: 3.8
Classifier: Programming Language :: Python :: 3.9
Classifier: Programming Language :: Python :: Implementation :: CPython
Classifier: Programming Language :: Python :: Implementation :: PyPy
Classifier: Natural Language :: English
Classifier: Operating System :: OS Independent
Classifier: Topic :: Internet :: WWW/HTTP
Classifier: Framework :: Zope :: 3
Requires-Dist: setuptools
Requires-Dist: zope.container
Requires-Dist: zope.component
Requires-Dist: zope.interface
Requires-Dist: zope.location
Requires-Dist: zope.publisher
Requires-Dist: zope.schema
Requires-Dist: zope.security
Requires-Dist: zope.traversing
Provides-Extra: docs
Requires-Dist: Sphinx ; extra == 'docs'
Requires-Dist: repoze.sphinx.autointerface ; extra == 'docs'
Requires-Dist: sphinx-rtd-theme ; extra == 'docs'
Provides-Extra: skin
Requires-Dist: zope.app.rotterdam ; extra == 'skin'
Provides-Extra: test
Requires-Dist: zope.app.rotterdam ; extra == 'test'
Requires-Dist: zope.browserpage ; extra == 'test'
Requires-Dist: zope.browserresource ; extra == 'test'
Requires-Dist: zope.configuration ; extra == 'test'
Requires-Dist: zope.security ; extra == 'test'
Requires-Dist: zope.testing ; extra == 'test'
Requires-Dist: zope.testrunner ; extra == 'test'
